README.md
setup.cfg
setup.py
TruckersMP/__init__.py
TruckersMP/api.py
TruckersMP/requests.py
TruckersMP.egg-info/PKG-INFO
TruckersMP.egg-info/SOURCES.txt
TruckersMP.egg-info/dependency_links.txt
TruckersMP.egg-info/not-zip-safe
TruckersMP.egg-info/requires.txt
TruckersMP.egg-info/top_level.txt
TruckersMP/exceptions/HTTPError.py
TruckersMP/exceptions/TruckersMPError.py
TruckersMP/models/bans.py
TruckersMP/models/events.py
TruckersMP/models/members.py
TruckersMP/models/news.py
TruckersMP/models/player.py
TruckersMP/models/roles.py
TruckersMP/models/rules.py
TruckersMP/models/servers.py
TruckersMP/models/versions.py
TruckersMP/models/vtcs.py