Metadata-Version: 2.1
Name: TruckersMP
Version: 1.0.1
Summary: Fully async python wrapper for TruckersMP API
Home-page: https://github.com/Belyashik2K/TruckersMP
Author: Belyashik2K
Author-email: lovelybelyashik@gmail.com
License: Apache License, Version 2.0
